README.rst
setup.cfg
setup.py
tornado_testing/__init__.py
tornado_testing/layer.py
tornado_testing/tests.py
tornado_testing.egg-info/PKG-INFO
tornado_testing.egg-info/SOURCES.txt
tornado_testing.egg-info/dependency_links.txt
tornado_testing.egg-info/requires.txt
tornado_testing.egg-info/top_level.txt