Metadata-Version: 1.1
Name: tornado-testing
Version: 0.2.0
Summary: tornado testlayer for use with zope.testrunner
Home-page: https://github.com/mfussenegger/tornado-testing
Author: Mathias Fußenegger
Author-email: pip@zignar.net
License: UNKNOWN
Platform: any
Classifier: Programming Language :: Python
Classifier: Programming Language :: Python :: 3
Classifier: Programming Language :: Python :: 3.4
Classifier: Programming Language :: Python :: Implementation :: CPython
